{
  "reconstructor": "DDPM (arbitrary-mask, guidance w=1)",
  "guidance": 1.0,
  "metric": "per-lead dipolar-projection RMSE (mV): e_l^T (M_s M_s^+)(Lhat-Ltrue)",
  "configs": [
    "limb-6",
    "{I,II,V1,V3,V5}"
  ],
  "segments": [
    "QRS",
    "ST",
    "T"
  ],
  "floor": {
    "floor_violation_frac": 0.0,
    "floor_gap_median_mV": 0.07923,
    "median_rmse_eta0": 0.06581,
    "median_rmse_etapos": 0.22695,
    "n_cells": 39
  },
  "cells": [
    {
      "config": "limb-6",
      "segment": "QRS",
      "lead": "V1",
      "eta": 0.29746,
      "kappa": 0.6085,
      "amb_mV": 0.20826,
      "eta_zero": false,
      "ddpm_rmse_mV": 0.2318,
      "n_records": 300
    },
    {
      "config": "limb-6",
      "segment": "QRS",
      "lead": "V2",
      "eta": 0.65392,
      "kappa": 0.5226,
      "amb_mV": 0.45783,
      "eta_zero": false,
      "ddpm_rmse_mV": 0.50115,
      "n_records": 300
    },
    {
      "config": "limb-6",
      "segment": "QRS",
      "lead": "V3",
      "eta": 0.59913,
      "kappa": 0.2353,
      "amb_mV": 0.41947,
      "eta_zero": false,
      "ddpm_rmse_mV": 0.49123,
      "n_records": 300
    },
    {
      "config": "limb-6",
      "segment": "QRS",
      "lead": "V4",
      "eta": 0.33511,
      "kappa": 0.8385,
      "amb_mV": 0.23462,
      "eta_zero": false,
      "ddpm_rmse_mV": 0.34987,
      "n_records": 300
    },
    {
      "config": "limb-6",
      "segment": "QRS",
      "lead": "V5",
      "eta": 0.10988,
      "kappa": 0.9287,
      "amb_mV": 0.07693,
      "eta_zero": false,
      "ddpm_rmse_mV": 0.22251,
      "n_records": 300
    },
    {
      "config": "limb-6",
      "segment": "QRS",
      "lead": "V6",
      "eta": 0.02418,
      "kappa": 0.7818,
      "amb_mV": 0.01693,
      "eta_zero": false,
      "ddpm_rmse_mV": 0.1491,
      "n_records": 300
    },
    {
      "config": "limb-6",
      "segment": "ST",
      "lead": "V1",
      "eta": 0.30723,
      "kappa": 0.5458,
      "amb_mV": 0.08379,
      "eta_zero": false,
      "ddpm_rmse_mV": 0.1445,
      "n_records": 300
    },
    {
      "config": "limb-6",
      "segment": "ST",
      "lead": "V2",
      "eta": 0.71358,
      "kappa": 0.3711,
      "amb_mV": 0.19461,
      "eta_zero": false,
      "ddpm_rmse_mV": 0.37048,
      "n_records": 300
    },
    {
      "config": "limb-6",
      "segment": "ST",
      "lead": "V3",
      "eta": 0.56535,
      "kappa": 0.3517,
      "amb_mV": 0.15418,
      "eta_zero": false,
      "ddpm_rmse_mV": 0.33772,
      "n_records": 300
    },
    {
      "config": "limb-6",
      "segment": "ST",
      "lead": "V4",
      "eta": 0.26483,
      "kappa": 0.937,
      "amb_mV": 0.07222,
      "eta_zero": false,
      "ddpm_rmse_mV": 0.23138,
      "n_records": 300
    },
    {
      "config": "limb-6",
      "segment": "ST",
      "lead": "V5",
      "eta": 0.04785,
      "kappa": 1.2384,
      "amb_mV": 0.01305,
      "eta_zero": false,
      "ddpm_rmse_mV": 0.17091,
      "n_records": 300
    },
    {
      "config": "limb-6",
      "segment": "ST",
      "lead": "V6",
      "eta": 0.06618,
      "kappa": 1.1239,
      "amb_mV": 0.01805,
      "eta_zero": false,
      "ddpm_rmse_mV": 0.12677,
      "n_records": 300
    },
    {
      "config": "limb-6",
      "segment": "T",
      "lead": "V1",
      "eta": 0.2847,
      "kappa": 0.5367,
      "amb_mV": 0.07256,
      "eta_zero": false,
      "ddpm_rmse_mV": 0.13228,
      "n_records": 300
    },
    {
      "config": "limb-6",
      "segment": "T",
      "lead": "V2",
      "eta": 0.73579,
      "kappa": 0.2276,
      "amb_mV": 0.18752,
      "eta_zero": false,
      "ddpm_rmse_mV": 0.37653,
      "n_records": 300
    },
    {
      "config": "limb-6",
      "segment": "T",
      "lead": "V3",
      "eta": 0.55985,
      "kappa": 0.3909,
      "amb_mV": 0.14268,
      "eta_zero": false,
      "ddpm_rmse_mV": 0.32795,
      "n_records": 300
    },
    {
      "config": "limb-6",
      "segment": "T",
      "lead": "V4",
      "eta": 0.24189,
      "kappa": 0.8118,
      "amb_mV": 0.06165,
      "eta_zero": false,
      "ddpm_rmse_mV": 0.21014,
      "n_records": 300
    },
    {
      "config": "limb-6",
      "segment": "T",
      "lead": "V5",
      "eta": 0.02258,
      "kappa": 1.2374,
      "amb_mV": 0.00575,
      "eta_zero": false,
      "ddpm_rmse_mV": 0.16843,
      "n_records": 300
    },
    {
      "config": "limb-6",
      "segment": "T",
      "lead": "V6",
      "eta": 0.07138,
      "kappa": 0.9686,
      "amb_mV": 0.01819,
      "eta_zero": false,
      "ddpm_rmse_mV": 0.12355,
      "n_records": 300
    },
    {
      "config": "{I,II,V1,V3,V5}",
      "segment": "QRS",
      "lead": "III",
      "eta": 0.0,
      "kappa": 1.3832,
      "amb_mV": 0.0,
      "eta_zero": true,
      "ddpm_rmse_mV": 0.09436,
      "n_records": 300
    },
    {
      "config": "{I,II,V1,V3,V5}",
      "segment": "QRS",
      "lead": "aVR",
      "eta": 0.0,
      "kappa": 0.3954,
      "amb_mV": 0.0,
      "eta_zero": true,
      "ddpm_rmse_mV": 0.04498,
      "n_records": 300
    },
    {
      "config": "{I,II,V1,V3,V5}",
      "segment": "QRS",
      "lead": "aVL",
      "eta": 0.0,
      "kappa": 1.0638,
      "amb_mV": 0.0,
      "eta_zero": true,
      "ddpm_rmse_mV": 0.07923,
      "n_records": 300
    },
    {
      "config": "{I,II,V1,V3,V5}",
      "segment": "QRS",
      "lead": "aVF",
      "eta": 0.0,
      "kappa": 1.048,
      "amb_mV": 0.0,
      "eta_zero": true,
      "ddpm_rmse_mV": 0.06847,
      "n_records": 300
    },
    {
      "config": "{I,II,V1,V3,V5}",
      "segment": "QRS",
      "lead": "V2",
      "eta": 0.0,
      "kappa": 1.2472,
      "amb_mV": 0.0,
      "eta_zero": true,
      "ddpm_rmse_mV": 0.154,
      "n_records": 300
    },
    {
      "config": "{I,II,V1,V3,V5}",
      "segment": "QRS",
      "lead": "V4",
      "eta": 0.0,
      "kappa": 0.7919,
      "amb_mV": 0.0,
      "eta_zero": true,
      "ddpm_rmse_mV": 0.08303,
      "n_records": 300
    },
    {
      "config": "{I,II,V1,V3,V5}",
      "segment": "QRS",
      "lead": "V6",
      "eta": 0.0,
      "kappa": 0.5865,
      "amb_mV": 0.0,
      "eta_zero": true,
      "ddpm_rmse_mV": 0.06513,
      "n_records": 300
    },
    {
      "config": "{I,II,V1,V3,V5}",
      "segment": "ST",
      "lead": "III",
      "eta": 0.0,
      "kappa": 1.0984,
      "amb_mV": 0.0,
      "eta_zero": true,
      "ddpm_rmse_mV": 0.06581,
      "n_records": 300
    },
    {
      "config": "{I,II,V1,V3,V5}",
      "segment": "ST",
      "lead": "aVR",
      "eta": 0.0,
      "kappa": 0.5227,
      "amb_mV": 0.0,
      "eta_zero": true,
      "ddpm_rmse_mV": 0.0255,
      "n_records": 300
    },
    {
      "config": "{I,II,V1,V3,V5}",
      "segment": "ST",
      "lead": "aVL",
      "eta": 0.0,
      "kappa": 0.6679,
      "amb_mV": 0.0,
      "eta_zero": true,
      "ddpm_rmse_mV": 0.05197,
      "n_records": 300
    },
    {
      "config": "{I,II,V1,V3,V5}",
      "segment": "ST",
      "lead": "aVF",
      "eta": 0.0,
      "kappa": 1.0225,
      "amb_mV": 0.0,
      "eta_zero": true,
      "ddpm_rmse_mV": 0.05004,
      "n_records": 300
    },
    {
      "config": "{I,II,V1,V3,V5}",
      "segment": "ST",
      "lead": "V2",
      "eta": 0.0,
      "kappa": 1.1613,
      "amb_mV": 0.0,
      "eta_zero": true,
      "ddpm_rmse_mV": 0.10114,
      "n_records": 300
    },
    {
      "config": "{I,II,V1,V3,V5}",
      "segment": "ST",
      "lead": "V4",
      "eta": 0.0,
      "kappa": 0.6985,
      "amb_mV": 0.0,
      "eta_zero": true,
      "ddpm_rmse_mV": 0.06994,
      "n_records": 300
    },
    {
      "config": "{I,II,V1,V3,V5}",
      "segment": "ST",
      "lead": "V6",
      "eta": 0.0,
      "kappa": 0.7854,
      "amb_mV": 0.0,
      "eta_zero": true,
      "ddpm_rmse_mV": 0.07999,
      "n_records": 300
    },
    {
      "config": "{I,II,V1,V3,V5}",
      "segment": "T",
      "lead": "III",
      "eta": 0.0,
      "kappa": 1.0894,
      "amb_mV": 0.0,
      "eta_zero": true,
      "ddpm_rmse_mV": 0.06327,
      "n_records": 300
    },
    {
      "config": "{I,II,V1,V3,V5}",
      "segment": "T",
      "lead": "aVR",
      "eta": 0.0,
      "kappa": 0.5226,
      "amb_mV": 0.0,
      "eta_zero": true,
      "ddpm_rmse_mV": 0.02664,
      "n_records": 300
    },
    {
      "config": "{I,II,V1,V3,V5}",
      "segment": "T",
      "lead": "aVL",
      "eta": 0.0,
      "kappa": 0.6602,
      "amb_mV": 0.0,
      "eta_zero": true,
      "ddpm_rmse_mV": 0.05219,
      "n_records": 300
    },
    {
      "config": "{I,II,V1,V3,V5}",
      "segment": "T",
      "lead": "aVF",
      "eta": 0.0,
      "kappa": 1.0165,
      "amb_mV": 0.0,
      "eta_zero": true,
      "ddpm_rmse_mV": 0.04692,
      "n_records": 300
    },
    {
      "config": "{I,II,V1,V3,V5}",
      "segment": "T",
      "lead": "V2",
      "eta": 0.0,
      "kappa": 1.1964,
      "amb_mV": 0.0,
      "eta_zero": true,
      "ddpm_rmse_mV": 0.10884,
      "n_records": 300
    },
    {
      "config": "{I,II,V1,V3,V5}",
      "segment": "T",
      "lead": "V4",
      "eta": 0.0,
      "kappa": 0.6341,
      "amb_mV": 0.0,
      "eta_zero": true,
      "ddpm_rmse_mV": 0.06397,
      "n_records": 300
    },
    {
      "config": "{I,II,V1,V3,V5}",
      "segment": "T",
      "lead": "V6",
      "eta": 0.0,
      "kappa": 0.6403,
      "amb_mV": 0.0,
      "eta_zero": true,
      "ddpm_rmse_mV": 0.07048,
      "n_records": 300
    }
  ],
  "lineage": {
    "commit": "2370ee266167f960de92d833908b070ba85adfe6",
    "git_dirty": true,
    "protocol": "recoverability-v2-2026-07",
    "protocol_sha256": "a2ff753529e4",
    "experiment_script": "certificate_floor_diffusion.py",
    "experiment_script_sha256": "adf642922487082c",
    "seed": 0,
    "targets": [
      "I",
      "II",
      "III",
      "aVR",
      "aVL",
      "aVF",
      "V1",
      "V2",
      "V3",
      "V4",
      "V5",
      "V6"
    ],
    "segment_def": "neurokit2-dwt on observed Lead II; P=Pon..Poff, QRS=Ron..Roff, ST=J..Ton, T=Ton..Toff",
    "normalization": "raw mV (DDPM reconstruction); dipolar-projection error",
    "dataset": {
      "name": "PTB-XL",
      "n_records": 21799,
      "ids_sha256": "d01d605b52faa1dd",
      "metadata_sha256": "7600de9c1b27d181"
    },
    "n_train": 1500,
    "n_test": 300,
    "train_ids_sha256": "4fd528172c55d714",
    "test_ids_sha256": "395bdb3da5a26ddf",
    "checkpoint_sha256": "9aad8b6f601ed9e4",
    "checkpoint": "/root/autodl-tmp/ecg-recoverability/results/gpu_ddpm.pt",
    "guidance": 1.0,
    "metric": "learned_model_vs_certified_floor",
    "configs": [
      "limb-6",
      "{I,II,V1,V3,V5}"
    ]
  }
}